basecommand/api/__init__.py
basecommand/api/aces.py
basecommand/api/basecommand.py
basecommand/api/datamover.py
basecommand/api/dataset.py
basecommand/api/dockerwrappers.py
basecommand/api/jobs.py
basecommand/api/kubewrappers.py
basecommand/api/measurements.py
basecommand/api/quickstart.py
basecommand/api/quickstart_cluster.py
basecommand/api/quickstart_project.py
basecommand/api/resource.py
basecommand/api/resultset.py
basecommand/api/search.py
basecommand/api/utils.py
basecommand/api/workspace.py
basecommand/command/__init__.py
basecommand/command/aces.py
basecommand/command/all_commands.py
basecommand/command/args_validation.py
basecommand/command/base_command.py
basecommand/command/batch.py
basecommand/command/completers.py
basecommand/command/data.py
basecommand/command/datamover/__init__.py
basecommand/command/datamover/export_dataset.py
basecommand/command/datamover/export_workspace.py
basecommand/command/datamover/import_dataset.py
basecommand/command/datamover/import_workspace.py
basecommand/command/datamover/utils.py
basecommand/command/datamover_command.py
basecommand/command/quickstart.py
basecommand/command/quickstart_cluster.py
basecommand/command/quickstart_project.py
basecommand/command/resource.py
basecommand/command/result.py
basecommand/command/workspace.py
basecommand/constants.py
basecommand/environ.py
basecommand/errors.py
basecommand/model/dataset.py
basecommand/printer/__init__.py
basecommand/printer/aces.py
basecommand/printer/batch.py
basecommand/printer/datamover.py
basecommand/printer/dataset.py
basecommand/printer/quickstart_cluster.py
basecommand/printer/quickstart_project.py
basecommand/printer/resource.py
basecommand/printer/result.py
basecommand/printer/workspace.py
basecommand/transfer/__init__.py
basecommand/transfer/upload_manager.py
basecommand/transformer/__init__.py
basecommand/transformer/dataset.py
basecommand/transformer/workspace.py
forge/__init__.py
forge/api/__init__.py
forge/api/allocation.py
forge/api/constraint.py
stg_ngcsdk-3.91.40.dist-info/METADATA
stg_ngcsdk-3.91.40.dist-info/WHEEL
stg_ngcsdk-3.91.40.dist-info/entry_points.txt
stg_ngcsdk-3.91.40.dist-info/RECORD
