Metadata-Version: 2.1
Name: stg-ngcsdk
Version: 3.91.40
Summary: NVIDIA GPU Cloud SDK
License: Apache 2.0
Author: NVIDIA CORPORATION
Requires-Python: >=3.9.16,<3.13
Classifier: License :: Other/Proprietary License
Classifier: Programming Language :: Python :: 3
Classifier: Programming Language :: Python :: 3.10
Classifier: Programming Language :: Python :: 3.11
Requires-Dist: Jinja2 (>=3.1.3,<4.0.0)
Requires-Dist: aiodns (>=3.0.0,<4.0.0)
Requires-Dist: aiohttp (>=3.9.3,<4.0.0)
Requires-Dist: argcomplete (>=1.12.3,<2.0.0)
Requires-Dist: boto3 (>=1.20.5,<2.0.0)
Requires-Dist: certifi (>=2023.7.22,<2024.0.0)
Requires-Dist: coverage (>=6.1.2,<7.0.0)
Requires-Dist: cryptography (>=42.0.4,<43.0.0)
Requires-Dist: dnspython (>=2.1.0,<3.0.0)
Requires-Dist: docker (>=6.1.3,<7.0.0)
Requires-Dist: docker-pycreds (>=0.4.0,<0.5.0)
Requires-Dist: google-api-core (>=2.2.2,<3.0.0)
Requires-Dist: grpcio (>=1.56.0,<2.0.0)
Requires-Dist: isodate (>=0.6.0,<0.7.0)
Requires-Dist: opentelemetry-exporter-otlp-proto-grpc (>=1.20.0,<2.0.0)
Requires-Dist: opentelemetry-instrumentation (>=0.41b0,<0.42)
Requires-Dist: opentelemetry-sdk (>=1.20.0,<2.0.0)
Requires-Dist: packaging (>=21.2,<22.0)
Requires-Dist: polling2 (>=0.5.0,<0.6.0)
Requires-Dist: prettytable (==2.0.0)
Requires-Dist: protobuf (>=3.19.5,<=3.20.3)
Requires-Dist: psutil (>=5.8.0,<6.0.0)
Requires-Dist: python-dateutil (>=2.8.2,<3.0.0)
Requires-Dist: requests (>=2.26.0,<3.0.0)
Requires-Dist: requests-toolbelt (>=1.0.0,<2.0.0)
Requires-Dist: rich (==12.6.0)
Requires-Dist: semver (>=2.13.0,<3.0.0)
Requires-Dist: shortuuid (>=1.0.11,<2.0.0)
Requires-Dist: urllib3 (>=1.26.17,<2.0.0)
Requires-Dist: validators (>=0.18.2,<0.19.0)
Requires-Dist: websocket-client (==1.3.1)
Project-URL: Documentation, https://docs.ngc.nvidia.com/sdk/
Project-URL: Homepage, https://ngc.nvidia.com/
